aniate/__init__.py
aniate/auth.py
aniate/cli.py
aniate/config.py
aniate/engine.py
aniate/marketplace.py
aniate/utils.py
aniate/brews/__init__.py
aniate/brews/document_storage/__init__.py
aniate/brews/document_storage/fetch.py
aniate/brews/document_storage/files.py
aniate/brews/document_storage/save.py
aniate/brews/secrets/__init__.py
aniate/brews/secrets/secrets.py
aniate/brews/tools/__init__.py
aniate/brews/tools/fix.py
aniate/brews/tools/review.py
aniate/brews/tools/shell.py
aniate/commands/__init__.py
aniate/commands/chat.py
aniate/commands/core.py
aniate/commands/net.py
aniate-1.2.8.dist-info/METADATA
aniate-1.2.8.dist-info/WHEEL
aniate-1.2.8.dist-info/entry_points.txt
aniate-1.2.8.dist-info/RECORD
