Metadata-Version: 2.4
Name: aniate
Version: 1.2.8
Summary: Terminal-first AI intelligence layer
Project-URL: Homepage, https://aniate.com
Project-URL: Documentation, https://docs.aniate.com
Project-URL: Repository, https://github.com/aniate/aniate
Project-URL: Issues, https://github.com/aniate/aniate/issues
Author-email: Kabir Murjani <kabirmurjani@gmail.com>
License-Expression: MIT
Keywords: ai,assistant,cli,copilot,llm,terminal
Classifier: Development Status :: 4 - Beta
Classifier: Environment :: Console
Classifier: Intended Audience :: Developers
Classifier: License :: OSI Approved :: MIT License
Classifier: Operating System :: OS Independent
Classifier: Programming Language :: Python :: 3
Classifier: Programming Language :: Python :: 3.10
Classifier: Programming Language :: Python :: 3.11
Classifier: Programming Language :: Python :: 3.12
Classifier: Topic :: Software Development
Classifier: Topic :: Utilities
Requires-Python: >=3.10
Requires-Dist: groq>=0.4.0
Requires-Dist: python-dotenv>=1.0.0
Requires-Dist: requests>=2.28.0
Requires-Dist: rich>=13.0.0
Requires-Dist: supabase>=2.0.0
Requires-Dist: typer>=0.9.0
Provides-Extra: dev
Requires-Dist: black>=23.0.0; extra == 'dev'
Requires-Dist: build>=1.0.0; extra == 'dev'
Requires-Dist: pytest>=7.0.0; extra == 'dev'
Requires-Dist: ruff>=0.1.0; extra == 'dev'
Requires-Dist: twine>=4.0.0; extra == 'dev'
